easypcd/__init__.py
easypcd/easypcd.py
easypcd/test.py
easypcd/utils.py
easypcd-0.0.33.dist-info/METADATA
easypcd-0.0.33.dist-info/WHEEL
easypcd-0.0.33.dist-info/top_level.txt
easypcd-0.0.33.dist-info/RECORD
