Metadata-Version: 2.1
Name: easypcd
Version: 0.0.33
Summary: a package for pcd
Home-page: https://gitee.com/wang2wan/easypcd_project
Author: GentleWang
Author-email: 189030005@stu.just.edu.cn
License: MIT
Classifier: Programming Language :: Python :: 3
Classifier: License :: OSI Approved :: MIT License
Classifier: Operating System :: OS Independent
Requires-Python: >=3.6
Requires-Dist: numpy
Requires-Dist: scipy
